ublame/__init__.py
ublame-0.1.0.dist-info/LICENSE
ublame-0.1.0.dist-info/METADATA
ublame-0.1.0.dist-info/WHEEL
ublame-0.1.0.dist-info/entry_points.txt
ublame-0.1.0.dist-info/top_level.txt
ublame-0.1.0.dist-info/RECORD
