Metadata-Version: 2.1
Name: ublame
Version: 0.1.0
Summary: Add some depth to `git blame`
Home-page: https://github.com/KraYmer/ublame
Author: Fabrice Laporte
Author-email: kraymer@gmail.com
License: MIT
Keywords: git
Platform: ALL
Classifier: License :: OSI Approved :: MIT License
Classifier: Programming Language :: Python
Classifier: Environment :: Console
Classifier: Topic :: System :: Filesystems
Requires-Dist: pydriller
Requires-Dist: click
Requires-Dist: blessed
Provides-Extra: test
Requires-Dist: coverage (<6,>=5) ; extra == 'test'
Requires-Dist: nose (>1.3) ; extra == 'test'
Requires-Dist: tox (>=3) ; extra == 'test'
